odoo10_addon_account_bank_statement_import_mt940_nl_mollie-10.0.1.0.0.99.dev3-py3.8-nspkg.pth
odoo/addons/account_bank_statement_import_mt940_nl_mollie/README.rst
odoo/addons/account_bank_statement_import_mt940_nl_mollie/__init__.py
odoo/addons/account_bank_statement_import_mt940_nl_mollie/__manifest__.py
odoo/addons/account_bank_statement_import_mt940_nl_mollie/examples/Voorbeeld MT-940.mt940
odoo/addons/account_bank_statement_import_mt940_nl_mollie/i18n/account_bank_statement_import_mt940_nl_mollie.pot
odoo/addons/account_bank_statement_import_mt940_nl_mollie/models/__init__.py
odoo/addons/account_bank_statement_import_mt940_nl_mollie/models/account_bank_statement_import.py
odoo/addons/account_bank_statement_import_mt940_nl_mollie/readme/CONTRIBUTORS.rst
odoo/addons/account_bank_statement_import_mt940_nl_mollie/readme/CREDITS.rst
odoo/addons/account_bank_statement_import_mt940_nl_mollie/readme/DESCRIPTION.rst
odoo/addons/account_bank_statement_import_mt940_nl_mollie/static/description/icon.png
odoo/addons/account_bank_statement_import_mt940_nl_mollie/static/description/index.html
odoo/addons/account_bank_statement_import_mt940_nl_mollie/tests/__init__.py
odoo/addons/account_bank_statement_import_mt940_nl_mollie/tests/test_account_bank_statement_import_mt940_nl_mollie.py
odoo/addons/account_bank_statement_import_mt940_nl_mollie/views/account_bank_statement_import.xml
odoo10_addon_account_bank_statement_import_mt940_nl_mollie-10.0.1.0.0.99.dev3.dist-info/METADATA
odoo10_addon_account_bank_statement_import_mt940_nl_mollie-10.0.1.0.0.99.dev3.dist-info/WHEEL
odoo10_addon_account_bank_statement_import_mt940_nl_mollie-10.0.1.0.0.99.dev3.dist-info/namespace_packages.txt
odoo10_addon_account_bank_statement_import_mt940_nl_mollie-10.0.1.0.0.99.dev3.dist-info/top_level.txt
odoo10_addon_account_bank_statement_import_mt940_nl_mollie-10.0.1.0.0.99.dev3.dist-info/RECORD
