Metadata-Version: 2.1
Name: odoo10-addon-account-bank-statement-import-mt940-nl-mollie
Version: 10.0.1.0.0.99.dev3
Summary: MT940 Bank Statements Import (Mollie)
Home-page: https://github.com/OCA/bank-statement-import
Author: Therp BV,Odoo Community Association (OCA)
Author-email: support@odoo-community.org
License: AGPL-3
Platform: UNKNOWN
Classifier: Programming Language :: Python
Classifier: Framework :: Odoo
Classifier: Framework :: Odoo :: 10.0
Classifier: License :: OSI Approved :: GNU Affero General Public License v3
Requires-Python: ~=2.7
Requires-Dist: odoo10-addon-account-bank-statement-import-mt940-base
Requires-Dist: odoo <10.1dev,>=10.0
